freezable/__init__.py
freezable/freezable.py
freezable-0.1.9.dist-info/LICENSE
freezable-0.1.9.dist-info/WHEEL
freezable-0.1.9.dist-info/METADATA
freezable-0.1.9.dist-info/RECORD
