Metadata-Version: 2.1
Name: freezable
Version: 0.1.9
Summary: Dynamically immutable objects
Home-page: https://github.com/ederic-oytas/python-freezable
License: MIT
Keywords: freeze,freezable,immutability,objects
Author: Ederic Oytas
Author-email: edericoytas@gmail.com
Requires-Python: >=3.7,<4.0
Classifier: Development Status :: 3 - Alpha
Classifier: License :: OSI Approved :: MIT License
Classifier: Programming Language :: Python :: 3
Classifier: Programming Language :: Python :: 3.10
Classifier: Programming Language :: Python :: 3.7
Classifier: Programming Language :: Python :: 3.8
Classifier: Programming Language :: Python :: 3.9
Project-URL: Repository, https://github.com/ederic-oytas/python-freezable
